petram/__init__.py
petram/phys/__init__.py
petram/phys/common/__init__.py
petram/phys/common/numba_zfunc.py
petram/phys/common/rf_dispersion_coldplasma.py
petram/phys/common/rf_dispersion_coldplasma_numba.py
petram/phys/common/rf_port_scanner.py
petram/phys/common/rf_stix_terms_panel.py
petram/phys/em1d/__init__.py
petram/phys/em1d/em1d_anisotropic.py
petram/phys/em1d/em1d_base.py
petram/phys/em1d/em1d_coldplasma.py
petram/phys/em1d/em1d_const.py
petram/phys/em1d/em1d_cont.py
petram/phys/em1d/em1d_e.py
petram/phys/em1d/em1d_extj.py
petram/phys/em1d/em1d_model.py
petram/phys/em1d/em1d_pec.py
petram/phys/em1d/em1d_pmc.py
petram/phys/em1d/em1d_port.py
petram/phys/em1d/em1d_vac.py
petram/phys/em1d/eval_deriv.py
petram/phys/em2d/__init__.py
petram/phys/em2d/em2d_anisotropic.py
petram/phys/em2d/em2d_base.py
petram/phys/em2d/em2d_coldplasma.py
petram/phys/em2d/em2d_cont.py
petram/phys/em2d/em2d_e.py
petram/phys/em2d/em2d_extj.py
petram/phys/em2d/em2d_floquet.py
petram/phys/em2d/em2d_h.py
petram/phys/em2d/em2d_model.py
petram/phys/em2d/em2d_pec.py
petram/phys/em2d/em2d_pmc.py
petram/phys/em2d/em2d_pml.py
petram/phys/em2d/em2d_vac.py
petram/phys/em2d/em2d_z.py
petram/phys/em2da/__init__.py
petram/phys/em2da/em2da_anisotropic.py
petram/phys/em2da/em2da_base.py
petram/phys/em2da/em2da_coldplasma.py
petram/phys/em2da/em2da_const.py
petram/phys/em2da/em2da_cont.py
petram/phys/em2da/em2da_e.py
petram/phys/em2da/em2da_extj.py
petram/phys/em2da/em2da_floquet.py
petram/phys/em2da/em2da_model.py
petram/phys/em2da/em2da_pec.py
petram/phys/em2da/em2da_pmc.py
petram/phys/em2da/em2da_port.py
petram/phys/em2da/em2da_surfj.py
petram/phys/em2da/em2da_vac.py
petram/phys/em2da/eval_deriv.py
petram/phys/em3d/__init__.py
petram/phys/em3d/em3d_anisotropic.py
petram/phys/em3d/em3d_base.py
petram/phys/em3d/em3d_coldplasma.py
petram/phys/em3d/em3d_const.py
petram/phys/em3d/em3d_cont.py
petram/phys/em3d/em3d_div.py
petram/phys/em3d/em3d_e.py
petram/phys/em3d/em3d_extj.py
PetraM_RF-1.5.7.dist-info/LICENSE
PetraM_RF-1.5.7.dist-info/METADATA
PetraM_RF-1.5.7.dist-info/WHEEL
PetraM_RF-1.5.7.dist-info/top_level.txt
PetraM_RF-1.5.7.dist-info/RECORD
